{"width":1024,"SubTexture":[{"width":798,"y":1,"height":648,"name":"dialog","x":1},{"width":63,"y":533,"height":90,"name":"ear_right","x":951},{"width":63,"y":1,"height":90,"name":"ear_left","x":956},{"width":308,"y":651,"height":401,"name":"face_base","x":1},{"width":148,"y":533,"height":92,"name":"mouth","x":801},{"width":158,"y":398,"height":133,"name":"mouth_su","x":801},{"width":118,"y":831,"height":41,"name":"tongue","x":847},{"width":86,"y":869,"height":51,"name":"tongue_su","x":311},{"width":148,"y":627,"height":48,"name":"teeth_su","x":847},{"width":107,"y":872,"height":31,"name":"teeth","x":509},{"width":69,"y":734,"height":35,"name":"nose","x":943},{"width":110,"y":189,"height":207,"name":"hair_left_shad","x":801},{"width":272,"y":651,"height":216,"name":"hair_right_shad","x":311},{"width":153,"y":1,"height":186,"name":"hair_left","x":801},{"width":260,"y":651,"height":219,"name":"hair_right","x":585},{"width":94,"y":754,"height":75,"name":"eye_left","x":847},{"width":96,"y":189,"height":98,"name":"eye_right_su","x":913},{"width":96,"y":289,"height":98,"name":"eye_left_su","x":913},{"width":94,"y":677,"height":75,"name":"eye_right","x":847},{"width":55,"y":93,"height":65,"name":"pupil_right_su","x":956},{"width":56,"y":456,"height":55,"name":"pupil_left","x":961},{"width":55,"y":389,"height":65,"name":"pupil_left_su","x":961},{"width":56,"y":677,"height":55,"name":"pupil_right","x":943},{"width":108,"y":869,"height":33,"name":"teeth_su_b","x":399}],"height":2048,"name":"Surprised_1","imagePath":"Surprised_1_tex.png"}